setfit/__init__.py
setfit/data.py
setfit/integrations.py
setfit/logging.py
setfit/losses.py
setfit/model_card.py
setfit/model_card_template.md
setfit/modeling.py
setfit/notebook.py
setfit/sampler.py
setfit/trainer.py
setfit/trainer_distillation.py
setfit/training_args.py
setfit/utils.py
setfit/exporters/__init__.py
setfit/exporters/onnx.py
setfit/exporters/openvino.py
setfit/exporters/utils.py
setfit/span/__init__.py
setfit/span/aspect_extractor.py
setfit/span/modeling.py
setfit/span/trainer.py
setfit-1.1.3.dist-info/licenses/LICENSE
setfit-1.1.3.dist-info/METADATA
setfit-1.1.3.dist-info/WHEEL
setfit-1.1.3.dist-info/top_level.txt
setfit-1.1.3.dist-info/RECORD
