Metadata-Version: 2.4
Name: setfit
Version: 1.1.3
Summary: Efficient few-shot learning with Sentence Transformers
Home-page: https://github.com/huggingface/setfit
Download-URL: https://github.com/huggingface/setfit/tags
Maintainer: Lewis Tunstall, Tom Aarsen
Maintainer-email: lewis@huggingface.co
License: Apache 2.0
Keywords: nlp,machine learning,fewshot learning,transformers
Classifier: Development Status :: 5 - Production/Stable
Classifier: Intended Audience :: Developers
Classifier: Intended Audience :: Education
Classifier: Intended Audience :: Science/Research
Classifier: License :: OSI Approved :: Apache Software License
Classifier: Operating System :: OS Independent
Classifier: Programming Language :: Python :: 3
Classifier: Programming Language :: Python :: 3.9
Classifier: Programming Language :: Python :: 3.10
Classifier: Programming Language :: Python :: 3.11
Classifier: Programming Language :: Python :: 3.12
Classifier: Topic :: Scientific/Engineering :: Artificial Intelligence
License-File: LICENSE
Requires-Dist: datasets>=2.15.0
Requires-Dist: sentence-transformers[train]>=3
Requires-Dist: transformers>=4.41.0
Requires-Dist: evaluate>=0.3.0
Requires-Dist: huggingface_hub>=0.24.0
Requires-Dist: scikit-learn
Requires-Dist: packaging
Provides-Extra: optuna
Requires-Dist: optuna; extra == "optuna"
Provides-Extra: quality
Requires-Dist: black; extra == "quality"
Requires-Dist: flake8; extra == "quality"
Requires-Dist: isort; extra == "quality"
Requires-Dist: tabulate; extra == "quality"
Provides-Extra: tests
Requires-Dist: pytest; extra == "tests"
Requires-Dist: pytest-cov; extra == "tests"
Requires-Dist: onnxruntime; extra == "tests"
Requires-Dist: onnx!=1.16.2; extra == "tests"
Requires-Dist: skl2onnx; extra == "tests"
Requires-Dist: hummingbird-ml; extra == "tests"
Requires-Dist: openvino; extra == "tests"
Requires-Dist: spacy<3.7.6; extra == "tests"
Provides-Extra: onnx
Requires-Dist: onnxruntime; extra == "onnx"
Requires-Dist: onnx!=1.16.2; extra == "onnx"
Requires-Dist: skl2onnx; extra == "onnx"
Provides-Extra: openvino
Requires-Dist: onnxruntime; extra == "openvino"
Requires-Dist: onnx!=1.16.2; extra == "openvino"
Requires-Dist: skl2onnx; extra == "openvino"
Requires-Dist: hummingbird-ml; extra == "openvino"
Requires-Dist: openvino; extra == "openvino"
Provides-Extra: docs
Requires-Dist: hf-doc-builder>=0.3.0; extra == "docs"
Provides-Extra: absa
Requires-Dist: spacy<3.7.6; extra == "absa"
Provides-Extra: codecarbon
Requires-Dist: codecarbon<2.6.0; extra == "codecarbon"
Provides-Extra: dev
Requires-Dist: tabulate; extra == "dev"
Requires-Dist: pytest-cov; extra == "dev"
Requires-Dist: black; extra == "dev"
Requires-Dist: codecarbon<2.6.0; extra == "dev"
Requires-Dist: isort; extra == "dev"
Requires-Dist: openvino; extra == "dev"
Requires-Dist: hummingbird-ml; extra == "dev"
Requires-Dist: pytest; extra == "dev"
Requires-Dist: spacy<3.7.6; extra == "dev"
Requires-Dist: onnxruntime; extra == "dev"
Requires-Dist: optuna; extra == "dev"
Requires-Dist: onnx!=1.16.2; extra == "dev"
Requires-Dist: hf-doc-builder>=0.3.0; extra == "dev"
Requires-Dist: skl2onnx; extra == "dev"
Requires-Dist: flake8; extra == "dev"
Provides-Extra: compat-tests
Requires-Dist: datasets==2.15.0; extra == "compat-tests"
Requires-Dist: sentence-transformers[train]==3; extra == "compat-tests"
Requires-Dist: transformers==4.41.0; extra == "compat-tests"
Requires-Dist: evaluate==0.3.0; extra == "compat-tests"
Requires-Dist: huggingface_hub==0.24.0; extra == "compat-tests"
Requires-Dist: scikit-learn; extra == "compat-tests"
Requires-Dist: packaging; extra == "compat-tests"
Requires-Dist: pytest; extra == "compat-tests"
Requires-Dist: pytest-cov; extra == "compat-tests"
Requires-Dist: onnxruntime; extra == "compat-tests"
Requires-Dist: onnx!=1.16.2; extra == "compat-tests"
Requires-Dist: skl2onnx; extra == "compat-tests"
Requires-Dist: hummingbird-ml; extra == "compat-tests"
Requires-Dist: openvino; extra == "compat-tests"
Requires-Dist: spacy<3.7.6; extra == "compat-tests"
Requires-Dist: pandas<2; extra == "compat-tests"
Requires-Dist: fsspec<2023.12.0; extra == "compat-tests"
Dynamic: classifier
Dynamic: description
Dynamic: description-content-type
Dynamic: download-url
Dynamic: home-page
Dynamic: keywords
Dynamic: license
Dynamic: license-file
Dynamic: maintainer
Dynamic: maintainer-email
Dynamic: provides-extra
Dynamic: requires-dist
Dynamic: summary
